simple_sign/__init__.py
simple_sign/sign.py
simple_sign/version.py
simple_sign-0.0.1.dist-info/LICENSE
simple_sign-0.0.1.dist-info/METADATA
simple_sign-0.0.1.dist-info/WHEEL
simple_sign-0.0.1.dist-info/entry_points.txt
simple_sign-0.0.1.dist-info/top_level.txt
simple_sign-0.0.1.dist-info/RECORD
