Metadata-Version: 2.1
Name: simple-sign
Version: 0.0.1
Summary: helper functions signing simple data using Cardano primitives
Author-email: "R. Spencer" <ross@orcfax.io>, George Orcfax <george@orcfax.io>
Project-URL: Homepage, https://orcfax.io/
Project-URL: Bug Reports, https://github.com/orcfax/simple-sign/issues/
Project-URL: Source, https://github.com/orcfax/simple-sign/
Keywords: cardano,signing,cip-8
Classifier: Development Status :: 3 - Alpha
Classifier: Intended Audience :: Developers
Classifier: License :: OSI Approved :: Apache Software License
Classifier: Programming Language :: Python :: 3
Classifier: Programming Language :: Python :: 3.10
Classifier: Programming Language :: Python :: 3.11
Classifier: Programming Language :: Python :: 3.12
Classifier: Programming Language :: Python :: 3 :: Only
Requires-Python: >=3.10
License-File: LICENSE
Requires-Dist: pycardano==0.12.0
